{"stats":{"minecraft:dropped":{"minecraft:iron_ingot":3,"minecraft:wheat_seeds":1,"minecraft:rotten_flesh":2,"minecraft:bamboo":3,"minecraft:white_wool":2},"minecraft:crafted":{"minecraft:cooked_beef":18,"minecraft:cooked_porkchop":5,"minecraft:stick":4,"minecraft:iron_ingot":2,"minecraft:torch":12,"minecraft:cooked_mutton":4,"minecraft:jungle_planks":4},"minecraft:picked_up":{"minecraft:crafting_table":1,"minecraft:raw_iron":2,"minecraft:cooked_porkchop":2,"minecraft:jungle_log":54,"minecraft:leather":6,"minecraft:torch":3,"minecraft:porkchop":7,"minecraft:pointed_dripstone":9,"minecraft:white_bed":2,"minecraft:gunpowder":6,"minecraft:dirt":19,"minecraft:raw_copper":26,"minecraft:rotten_flesh":2,"minecraft:stone_axe":1,"minecraft:wheat_seeds":4,"minecraft:iron_ingot":2,"minecraft:beef":10,"minecraft:stone_pickaxe":1,"minecraft:jungle_sapling":2,"minecraft:iron_pickaxe":1,"minecraft:bamboo":3,"minecraft:melon_slice":79,"minecraft:sugar_cane":1,"minecraft:mutton":3,"minecraft:coal":34,"minecraft:white_wool":2,"minecraft:cobblestone":20,"minecraft:furnace":2},"minecraft:mined":{"minecraft:white_bed":1,"minecraft:furnace":2,"minecraft:iron_ore":2,"minecraft:crafting_table":1,"minecraft:short_grass":64,"minecraft:pointed_dripstone":2,"minecraft:grass_block":1,"minecraft:coal_ore":24,"minecraft:melon":11,"minecraft:dirt":1,"minecraft:copper_ore":8,"minecraft:wall_torch":3,"minecraft:stone":20,"minecraft:fern":13},"minecraft:used":{"minecraft:jungle_sapling":2,"minecraft:stone_pickaxe":60,"minecraft:melon_slice":28,"minecraft:torch":6,"minecraft:stone_axe":56,"minecraft:dirt":9,"minecraft:white_bed":1,"minecraft:pointed_dripstone":9},"minecraft:custom":{"minecraft:time_since_rest":4455,"minecraft:interact_with_furnace":26,"minecraft:sprint_one_cm":122406,"minecraft:damage_taken":432,"minecraft:walk_one_cm":127257,"minecraft:mob_kills":11,"minecraft:drop":11,"minecraft:damage_dealt":1321,"minecraft:interact_with_crafting_table":5,"minecraft:fly_one_cm":20118,"minecraft:crouch_one_cm":234,"minecraft:play_time":33093,"minecraft:sneak_time":88,"minecraft:walk_under_water_one_cm":4018,"minecraft:boat_one_cm":26289,"minecraft:jump":315,"minecraft:leave_game":1,"minecraft:sleep_in_bed":1,"minecraft:walk_on_water_one_cm":5791,"minecraft:time_since_death":33093,"minecraft:climb_one_cm":163,"minecraft:total_world_time":33093,"minecraft:fall_one_cm":5422},"minecraft:killed":{"minecraft:skeleton":1,"minecraft:sheep":1,"minecraft:zombie":1,"minecraft:pig":1,"minecraft:drowned":2,"minecraft:cow":5}},"DataVersion":4082}